fairdatapoint-0.7.2.data/scripts/fdp-run
fdp/__init__.py
fdp/__version__.py
fdp/config.py
fdp/fairgraph.py
fdp/fdp.py
fdp/validator.py
fdp/api/__init__.py
fdp/api/metadata.py
fdp/openapi/openapi.yaml
fdp/schema/catalog.shacl
fdp/schema/dataset.shacl
fdp/schema/distribution.shacl
fdp/schema/fdp.shacl
fairdatapoint-0.7.2.dist-info/LICENSE
fairdatapoint-0.7.2.dist-info/METADATA
fairdatapoint-0.7.2.dist-info/WHEEL
fairdatapoint-0.7.2.dist-info/top_level.txt
fairdatapoint-0.7.2.dist-info/RECORD
