Metadata-Version: 2.1
Name: fairdatapoint
Version: 0.7.2
Summary: Python implementation of FAIR Data Point
Home-page: https://github.com/NLeSC/fairdatapoint
Author: Rajaram Kaliyaperumal, Arnold Kuzniar, Cunliang Geng, Carlos Martinez-Ortiz
Author-email: c.martinez@esciencecenter.nl
License: Apache Software License 2.0
Keywords: fdp,fairdatapoint
Platform: UNKNOWN
Classifier: Development Status :: 2 - Pre-Alpha
Classifier: Intended Audience :: Developers
Classifier: License :: OSI Approved :: Apache Software License
Classifier: Natural Language :: English
Classifier: Programming Language :: Python :: 3
Classifier: Programming Language :: Python :: 3.5
Classifier: Programming Language :: Python :: 3.6
Classifier: Programming Language :: Python :: 3.7
Requires-Dist: rdflib (==4.2.2)
Requires-Dist: rdflib-jsonld (==0.4.0)
Requires-Dist: docopt (==0.6.2)
Requires-Dist: Flask (==1.1.1)
Requires-Dist: Werkzeug (==0.16.0)
Requires-Dist: pyshacl (==0.11.4)
Requires-Dist: SPARQLWrapper (==1.8.5)
Requires-Dist: connexion (==2.7.0)
Requires-Dist: swagger-ui-bundle (>=0.0.2)
Provides-Extra: dev
Requires-Dist: prospector[with_pyroma] ; extra == 'dev'
Requires-Dist: yapf ; extra == 'dev'
Requires-Dist: isort ; extra == 'dev'
Requires-Dist: swagger-ui-bundle (>=0.0.2) ; extra == 'dev'
Provides-Extra: docs
Requires-Dist: sphinx ; extra == 'docs'
Requires-Dist: sphinx-rtd-theme ; extra == 'docs'
Requires-Dist: recommonmark ; extra == 'docs'
Provides-Extra: tests
Requires-Dist: pytest (>5.0) ; extra == 'tests'
Requires-Dist: pytest-cov ; extra == 'tests'
Requires-Dist: coveralls ; extra == 'tests'
Requires-Dist: pytest-datadir-ng ; extra == 'tests'
